CONTRIBUTING.rst
LICENSE.txt
MANIFEST.in
README.rst
pyproject.toml
requirements.txt
setup.cfg
setup.py
src/queuelink/__init__.py
src/queuelink/classtemplate.py
src/queuelink/exceptionhandler.py
src/queuelink/queuelink.py
src/queuelink/version.py
src/queuelink.egg-info/PKG-INFO
src/queuelink.egg-info/SOURCES.txt
src/queuelink.egg-info/dependency_links.txt
src/queuelink.egg-info/requires.txt
src/queuelink.egg-info/top_level.txt
src/queuelink/future/contentwrapper.py
src/queuelink/future/queue_pipe_adapter_base.py
src/queuelink/future/queue_pipe_adapter_reader.py
src/queuelink/future/queue_pipe_adapter_writer.py
src/queuelink/future/timer.py
src/queuelink/future/writeout.py