Metadata-Version: 2.1
Name: queuelink
Version: 1.0.0
Summary: Connect and link one or more Queues together or to files
Author-email: Andy Robb <andy@andyrobb.com>
License: MIT License
Project-URL: homepage, https://github.com/arobb/python-queuelink
Project-URL: repository, https://github.com/arobb/python-queuelink
Keywords: utility
Classifier: Intended Audience :: Developers
Classifier: Topic :: Utilities
Classifier: License :: OSI Approved :: MIT License
Classifier: Topic :: Software Development :: Libraries :: Python Modules
Provides-Extra: dev
Provides-Extra: test
Provides-Extra: docs
License-File: LICENSE.txt
